langlint-1.0.3.dist-info/METADATA
langlint-1.0.3.dist-info/WHEEL
langlint-1.0.3.dist-info/entry_points.txt
langlint/__init__.py
langlint/cli.py
langlint/langlint.exe
langlint/py.typed
langlint_py/__init__.py
langlint_py/langlint_py.cp311-win_amd64.pyd
langlint-1.0.3.dist-info/RECORD
