Metadata-Version: 2.4
Name: langlint
Version: 1.0.3
Classifier: Development Status :: 5 - Production/Stable
Classifier: Intended Audience :: Developers
Classifier: License :: OSI Approved :: MIT License
Classifier: Programming Language :: Python :: 3
Classifier: Programming Language :: Python :: 3.8
Classifier: Programming Language :: Python :: 3.9
Classifier: Programming Language :: Python :: 3.10
Classifier: Programming Language :: Python :: 3.11
Classifier: Programming Language :: Python :: 3.12
Classifier: Programming Language :: Rust
Requires-Dist: click>=8.0.0
Summary: High-performance automated translation platform powered by Rust
Keywords: translation,i18n,localization,rust,cli,automation,markdown,glossary
Author-email: Zhiang He <ang@hezhiang.com>
License: MIT
Requires-Python: >=3.8
Project-URL: Homepage, https://github.com/HzaCode/Langlint
Project-URL: Repository, https://github.com/HzaCode/Langlint.git
Project-URL: Issues, https://github.com/HzaCode/Langlint/issues
